ax/__ init __.py
ax/alembic.ini
ax/app.template.yaml
ax/appengine_config.py
ax/ax.sh
ax/field_types.yaml
ax/main.py
ax/backend/__ init __.py
ax/backend/auth.py
ax/backend/cache.py
ax/backend/dialects.py
ax/backend/emails.py
ax/backend/exec.py
ax/backend/graphqlview.py
ax/backend/logger.py
ax/backend/migration.py
ax/backend/misc.py
ax/backend/model.py
ax/backend/pubsub.py
ax/backend/routes.py
ax/backend/scheduler.py
ax/backend/schema.py
ax/backend/tus.py
ax/backend/alembic/__ init __.py
ax/backend/alembic/env.py
ax/backend/alembic/script.py.mako
ax/backend/alembic/versions/9b898740929f_baseline.py
ax/backend/alembic/versions/b3eb6ccd4b1f_added_options_json_to_action_role_form.py
ax/backend/fields/Ax1tom.py
ax/backend/fields/Ax1tomTable.py
ax/backend/fields/AxApproval.py
ax/backend/fields/AxAuthor.py
ax/backend/fields/AxChangelog.py
ax/backend/fields/AxComments.py
ax/backend/fields/AxDate.py
ax/backend/fields/AxFiles.py
ax/backend/fields/AxHtmlGenerated.py
ax/backend/fields/AxImageCropDb.py
ax/backend/fields/AxImageWebcamOverlay.py
ax/backend/fields/AxNum.py
ax/backend/fields/AxPaymentStripe.py
ax/backend/fields/__ init __.py
ax/backend/logs/ax_logs.log
ax/backend/schemas/__ init __.py
ax/backend/schemas/action_schema.py
ax/backend/schemas/fields_schema.py
ax/backend/schemas/form_schema.py
ax/backend/schemas/grids_schema.py
ax/backend/schemas/home_schema.py
ax/backend/schemas/marketplace_schema.py
ax/backend/schemas/pages_schema.py
ax/backend/schemas/types.py
ax/backend/schemas/users_schema.py
ax/backend/schemas/workflow_schema.py
ax/dist/ax/editor.worker.js
ax/dist/ax/editor.worker.js.LICENSE.txt
ax/dist/ax/html.worker.js
ax/dist/ax/html.worker.js.LICENSE.txt
ax/dist/ax/index.html
ax/dist/ax/json.worker.js
ax/dist/ax/json.worker.js.LICENSE.txt
ax/dist/ax/test.html
ax/dist/ax/static/android-chrome-192x192.png
ax/dist/ax/static/android-chrome-512x512.png
ax/dist/ax/static/android-chrome-96x96.png
ax/dist/ax/static/apple-touch-icon.png
ax-0.52.0.dist-info/LICENSE.md
ax-0.52.0.dist-info/METADATA
ax-0.52.0.dist-info/WHEEL
ax-0.52.0.dist-info/entry_points.txt
ax-0.52.0.dist-info/top_level.txt
ax-0.52.0.dist-info/RECORD
