Metadata-Version: 2.1
Name: ax
Version: 0.52.0
Summary: Ax - workflow apps builder
Home-page: https://github.com/enf644/ax
Author: Mikhail Marenov
Author-email: enf644@gmail.com
License: COMMERCIAL
Platform: UNKNOWN
Classifier: License :: Other/Proprietary License
Classifier: Topic :: Office/Business :: Groupware
Classifier: Topic :: Software Development
Classifier: Programming Language :: Python :: 3
Classifier: Development Status :: 1 - Planning
Requires-Dist: sanic (<=19.12.2)
Requires-Dist: Sanic-Cors (<=0.9.9.post4)
Requires-Dist: sanic-compress (<=0.1.1)
Requires-Dist: sanic-jwt (<=1.4.0)
Requires-Dist: Sanic-GraphQl (<=1.1.0)
Requires-Dist: SQLAlchemy (<=1.3.13)
Requires-Dist: sqlalchemy-utils (<=0.36.1)
Requires-Dist: alembic (<=1.3.3)
Requires-Dist: py-postgresql (<=1.2.1)
Requires-Dist: graphene (<=2.1.8)
Requires-Dist: graphene-sqlalchemy (<=2.2.2)
Requires-Dist: graphql-core (<=2.2.1)
Requires-Dist: graphql-relay (<=2.0.0)
Requires-Dist: graphql-ws (<=0.3.0)
Requires-Dist: aiohttp (<=3.6.2)
Requires-Dist: aiocache[redis] (<=0.11.1)
Requires-Dist: aiopubsub (<=2.1.5)
Requires-Dist: aiosmtplib (<=1.1.2)
Requires-Dist: APScheduler (<=3.6.3)
Requires-Dist: pyyaml (<=5.1.2)
Requires-Dist: ruamel.yaml (<=0.16.7)
Requires-Dist: loguru (<=0.4.1)
Requires-Dist: docopt (<=0.6.2)
Requires-Dist: packaging (<=20.1)
Requires-Dist: dotmap (<=1.3.8)
Requires-Dist: passlib (<=1.7.2)
Requires-Dist: markdown2 (<=2.3.8)
Requires-Dist: gunicorn (<=20.0.4)
Requires-Dist: rsa (<=4.0)
Requires-Dist: stripe (<=2.42.0)
Requires-Dist: python-dateutil (<=2.8.1)
